pydantic_super_model/__init__.py
pydantic_super_model/model.py
scripts/run_tests.py
pydantic_super_model-1.1.4.dist-info/LICENSE
pydantic_super_model-1.1.4.dist-info/METADATA
pydantic_super_model-1.1.4.dist-info/WHEEL
pydantic_super_model-1.1.4.dist-info/entry_points.txt
pydantic_super_model-1.1.4.dist-info/RECORD
