Metadata-Version: 2.3
Name: pydantic-super-model
Version: 1.1.4
Summary: Pydantic BaseModel supercharged with helper methods for generic and annotation support
License: MIT
Author: Julien Kmec
Author-email: me@julien.dev
Requires-Python: >=3.11,<3.15
Classifier: License :: OSI Approved :: MIT License
Classifier: Programming Language :: Python :: 3
Classifier: Programming Language :: Python :: 3.11
Classifier: Programming Language :: Python :: 3.12
Classifier: Programming Language :: Python :: 3.13
Provides-Extra: dev
Requires-Dist: black ; extra == "dev"
Requires-Dist: coverage (>=7.6) ; extra == "dev"
Requires-Dist: isort ; extra == "dev"
Requires-Dist: pydantic (>=2.11.7)
Requires-Dist: pylint ; extra == "dev"
Requires-Dist: pytest (>=8.0) ; extra == "dev"
Requires-Dist: pytest-asyncio (>=0.23) ; extra == "dev"
Requires-Dist: pytest-cov (>=6.1.1) ; extra == "dev"
Requires-Dist: python-generics (>=0.2.3)
